bball_cli/__init__.py
bball_cli/main.py
bball_cli/commands/__init__.py
bball_cli/commands/api.py
bball_cli/commands/data.py
bball_cli/commands/reports.py
bball_cli/commands/strategies.py
bball_cli-0.1.2.dist-info/METADATA
bball_cli-0.1.2.dist-info/WHEEL
bball_cli-0.1.2.dist-info/entry_points.txt
bball_cli-0.1.2.dist-info/RECORD
