Metadata-Version: 2.4
Name: bball-cli
Version: 0.1.2
Summary: Command-line interface for the bball ecosystem
Project-URL: Homepage, https://bball.dev
Project-URL: Documentation, https://docs.bball.dev
Project-URL: Repository, https://github.com/bball-dev/bball
Project-URL: Issues, https://github.com/bball-dev/bball/issues
Author-email: Nicholas Cooper <nicholascullencooper@gmail.com>
License: MIT
Keywords: analytics,basketball,data,nba,sports
Requires-Python: >=3.13
Requires-Dist: bball>=0.1.0
Requires-Dist: click>=8.1
Requires-Dist: rich>=13.0
Requires-Dist: typer>=0.12
